{
  "metadata": {
    "country_code": "bi",
    "country_name": "Burundi",
    "continent_code": "af",
    "continent_name": "Africa",
    "generated_at": "2026-04-17T06:47:16Z",
    "total_servers": 1
  },
  "resolvers": [
    {
      "ip": "41.79.47.6",
      "version": 4,
      "country_code": "bi",
      "country": "Burundi",
      "continent_code": "af",
      "continent": "Africa",
      "organization": "UCOM",
      "domain": null,
      "trusted": false,
      "anycast": false,
      "dnssec": {
        "aware": true,
        "validating": false
      },
      "blocking": {
        "ads": true,
        "malware": true,
        "adult": true
      },
      "uptime": {
        "24h": 66.67,
        "30d": 65.02,
        "90d": 73.02,
        "1y": 78.45
      }
    }
  ]
}
