{
  "metadata": {
    "country_code": "ie",
    "country_name": "Ireland",
    "continent_code": "eu",
    "continent_name": "Europe",
    "generated_at": "2026-02-23T06:33:22Z",
    "total_servers": 6
  },
  "resolvers": [
    {
      "ip": "84.203.162.227",
      "version": 4,
      "country_code": "ie",
      "country": "Ireland",
      "continent_code": "eu",
      "continent": "Europe",
      "organization": "Viatel Ltd",
      "domain": null,
      "trusted": false,
      "anycast": false,
      "dnssec": {
        "aware": false,
        "validating": false
      },
      "blocking": {
        "ads": false,
        "malware": true,
        "adult": true
      },
      "uptime": {
        "24h": 28.57,
        "30d": 61.61,
        "90d": 46.66,
        "1y": 48.31
      }
    },
    {
      "ip": "83.71.132.188",
      "version": 4,
      "country_code": "ie",
      "country": "Ireland",
      "continent_code": "eu",
      "continent": "Europe",
      "organization": "Shannonaerospace",
      "domain": null,
      "trusted": false,
      "anycast": false,
      "dnssec": {
        "aware": false,
        "validating": true
      },
      "blocking": {
        "ads": false,
        "malware": false,
        "adult": false
      },
      "uptime": {
        "24h": 100.0,
        "30d": 99.62,
        "90d": 98.27,
        "1y": 98.39
      }
    },
    {
      "ip": "86.43.125.181",
      "version": 4,
      "country_code": "ie",
      "country": "Ireland",
      "continent_code": "eu",
      "continent": "Europe",
      "organization": "Eircom",
      "domain": null,
      "trusted": false,
      "anycast": false,
      "dnssec": {
        "aware": true,
        "validating": false
      },
      "blocking": {
        "ads": true,
        "malware": true,
        "adult": true
      },
      "uptime": {
        "24h": 57.14,
        "30d": 58.77,
        "90d": 44.84,
        "1y": 45.32
      }
    },
    {
      "ip": "194.125.133.10",
      "version": 4,
      "country_code": "ie",
      "country": "Ireland",
      "continent_code": "eu",
      "continent": "Europe",
      "organization": "INDIGO",
      "domain": "ann.indigo.ie",
      "trusted": false,
      "anycast": false,
      "dnssec": {
        "aware": true,
        "validating": true
      },
      "blocking": {
        "ads": false,
        "malware": false,
        "adult": false
      },
      "uptime": {
        "24h": 100.0,
        "30d": 99.81,
        "90d": 99.93,
        "1y": 99.94
      }
    },
    {
      "ip": "78.155.252.220",
      "version": 4,
      "country_code": "ie",
      "country": "Ireland",
      "continent_code": "eu",
      "continent": "Europe",
      "organization": "NWE Wireless Networks Ltd.",
      "domain": null,
      "trusted": false,
      "anycast": false,
      "dnssec": {
        "aware": false,
        "validating": false
      },
      "blocking": {
        "ads": false,
        "malware": false,
        "adult": false
      },
      "uptime": {
        "24h": 85.71,
        "30d": 88.31,
        "90d": 94.38,
        "1y": 94.98
      }
    },
    {
      "ip": "88.87.181.244",
      "version": 4,
      "country_code": "ie",
      "country": "Ireland",
      "continent_code": "eu",
      "continent": "Europe",
      "organization": "EOBO Ltd T/A BBnet",
      "domain": null,
      "trusted": false,
      "anycast": false,
      "dnssec": {
        "aware": false,
        "validating": false
      },
      "blocking": {
        "ads": true,
        "malware": true,
        "adult": true
      },
      "uptime": {
        "24h": 57.14,
        "30d": 30.14,
        "90d": 24.08,
        "1y": 23.61
      }
    }
  ]
}
