{
  "metadata": {
    "country_code": "ir",
    "country_name": "Iran",
    "continent_code": "as",
    "continent_name": "Asia",
    "generated_at": "2026-04-09T06:41:47Z",
    "total_servers": 4
  },
  "resolvers": [
    {
      "ip": "217.218.155.155",
      "version": 4,
      "country_code": "ir",
      "country": "Iran",
      "continent_code": "as",
      "continent": "Asia",
      "organization": "\"Telecommunication Intfrastructure Company\" IP range.",
      "domain": "recursive2.dci.ir",
      "trusted": false,
      "anycast": false,
      "dnssec": {
        "aware": true,
        "validating": true
      },
      "blocking": {
        "ads": true,
        "malware": true,
        "adult": true
      },
      "uptime": {
        "24h": 100.0,
        "30d": 92.0,
        "90d": 92.71,
        "1y": 97.04
      }
    },
    {
      "ip": "194.225.62.80",
      "version": 4,
      "country_code": "ir",
      "country": "Iran",
      "continent_code": "as",
      "continent": "Asia",
      "organization": "TUMS Network",
      "domain": "ourdns1.tums.ac.ir",
      "trusted": false,
      "anycast": false,
      "dnssec": {
        "aware": true,
        "validating": true
      },
      "blocking": {
        "ads": true,
        "malware": true,
        "adult": true
      },
      "uptime": {
        "24h": 100.0,
        "30d": 74.63,
        "90d": 83.62,
        "1y": 95.44
      }
    },
    {
      "ip": "194.225.152.10",
      "version": 4,
      "country_code": "ir",
      "country": "Iran",
      "continent_code": "as",
      "continent": "Asia",
      "organization": "IPM/Iranet",
      "domain": "ns1.iranet.ir",
      "trusted": false,
      "anycast": false,
      "dnssec": {
        "aware": true,
        "validating": true
      },
      "blocking": {
        "ads": false,
        "malware": true,
        "adult": true
      },
      "uptime": {
        "24h": 100.0,
        "30d": 94.84,
        "90d": 97.45,
        "1y": 97.45
      }
    },
    {
      "ip": "217.218.127.127",
      "version": 4,
      "country_code": "ir",
      "country": "Iran",
      "continent_code": "as",
      "continent": "Asia",
      "organization": "\"Telecommunication Intfrastructure Company\" IP range.",
      "domain": "recursive1.dci.ir",
      "trusted": false,
      "anycast": false,
      "dnssec": {
        "aware": true,
        "validating": false
      },
      "blocking": {
        "ads": true,
        "malware": true,
        "adult": true
      },
      "uptime": {
        "24h": 100.0,
        "30d": 84.65,
        "90d": 90.44,
        "1y": 96.21
      }
    }
  ]
}
