{
  "metadata": {
    "country_code": "la",
    "country_name": "Laos",
    "continent_code": "as",
    "continent_name": "Asia",
    "generated_at": "2026-03-03T18:12:54Z",
    "total_servers": 4
  },
  "resolvers": [
    {
      "ip": "115.84.91.78",
      "version": 4,
      "country_code": "la",
      "country": "Laos",
      "continent_code": "as",
      "continent": "Asia",
      "organization": "Lao Telecommunication Public Company",
      "domain": null,
      "trusted": false,
      "anycast": false,
      "dnssec": {
        "aware": false,
        "validating": false
      },
      "blocking": {
        "ads": true,
        "malware": true,
        "adult": false
      },
      "uptime": {
        "24h": 100.0,
        "30d": 99.2,
        "90d": 90.11,
        "1y": 90.11
      }
    },
    {
      "ip": "43.252.244.118",
      "version": 4,
      "country_code": "la",
      "country": "Laos",
      "continent_code": "as",
      "continent": "Asia",
      "organization": "Enterprise of Telecommunications Lao",
      "domain": null,
      "trusted": false,
      "anycast": false,
      "dnssec": {
        "aware": false,
        "validating": false
      },
      "blocking": {
        "ads": false,
        "malware": false,
        "adult": false
      },
      "uptime": {
        "24h": 100.0,
        "30d": 85.03,
        "90d": 87.85,
        "1y": 88.86
      }
    },
    {
      "ip": "202.123.179.205",
      "version": 4,
      "country_code": "la",
      "country": "Laos",
      "continent_code": "as",
      "continent": "Asia",
      "organization": "Skytelecom , Transit provider and ISP in Vientiene.",
      "domain": null,
      "trusted": false,
      "anycast": false,
      "dnssec": {
        "aware": true,
        "validating": false
      },
      "blocking": {
        "ads": true,
        "malware": true,
        "adult": true
      },
      "uptime": {
        "24h": 100.0,
        "30d": 96.79,
        "90d": 90.98,
        "1y": 91.87
      }
    },
    {
      "ip": "115.84.79.71",
      "version": 4,
      "country_code": "la",
      "country": "Laos",
      "continent_code": "as",
      "continent": "Asia",
      "organization": "Lao Telecommunication Co Ltd",
      "domain": null,
      "trusted": false,
      "anycast": false,
      "dnssec": {
        "aware": false,
        "validating": false
      },
      "blocking": {
        "ads": false,
        "malware": true,
        "adult": true
      },
      "uptime": {
        "24h": 100.0,
        "30d": 95.99,
        "90d": 65.52,
        "1y": 68.84
      }
    }
  ]
}
