{
  "metadata": {
    "country_code": "la",
    "country_name": "Laos",
    "continent_code": "as",
    "continent_name": "Asia",
    "generated_at": "2026-03-05T06:24:16Z",
    "total_servers": 4
  },
  "resolvers": [
    {
      "ip": "115.84.91.78",
      "version": 4,
      "country_code": "la",
      "country": "Laos",
      "continent_code": "as",
      "continent": "Asia",
      "organization": "Lao Telecommunication Public Company",
      "domain": null,
      "trusted": false,
      "anycast": false,
      "dnssec": {
        "aware": false,
        "validating": false
      },
      "blocking": {
        "ads": false,
        "malware": true,
        "adult": false
      },
      "uptime": {
        "24h": 92.31,
        "30d": 98.89,
        "90d": 90.17,
        "1y": 90.17
      }
    },
    {
      "ip": "43.252.244.118",
      "version": 4,
      "country_code": "la",
      "country": "Laos",
      "continent_code": "as",
      "continent": "Asia",
      "organization": "Enterprise of Telecommunications Lao",
      "domain": null,
      "trusted": false,
      "anycast": false,
      "dnssec": {
        "aware": false,
        "validating": false
      },
      "blocking": {
        "ads": false,
        "malware": true,
        "adult": false
      },
      "uptime": {
        "24h": 100.0,
        "30d": 84.72,
        "90d": 87.69,
        "1y": 88.92
      }
    },
    {
      "ip": "202.123.179.205",
      "version": 4,
      "country_code": "la",
      "country": "Laos",
      "continent_code": "as",
      "continent": "Asia",
      "organization": "Skytelecom , Transit provider and ISP in Vientiene.",
      "domain": null,
      "trusted": false,
      "anycast": false,
      "dnssec": {
        "aware": true,
        "validating": true
      },
      "blocking": {
        "ads": false,
        "malware": true,
        "adult": true
      },
      "uptime": {
        "24h": 100.0,
        "30d": 96.94,
        "90d": 90.89,
        "1y": 91.89
      }
    },
    {
      "ip": "115.84.79.71",
      "version": 4,
      "country_code": "la",
      "country": "Laos",
      "continent_code": "as",
      "continent": "Asia",
      "organization": "Lao Telecommunication Co Ltd",
      "domain": null,
      "trusted": false,
      "anycast": false,
      "dnssec": {
        "aware": false,
        "validating": false
      },
      "blocking": {
        "ads": false,
        "malware": true,
        "adult": true
      },
      "uptime": {
        "24h": 100.0,
        "30d": 96.1,
        "90d": 65.55,
        "1y": 69.04
      }
    }
  ]
}
