{
  "metadata": {
    "country_code": "nz",
    "country_name": "New Zealand",
    "continent_code": "oc",
    "continent_name": "Oceania",
    "generated_at": "2026-04-13T06:54:54Z",
    "total_servers": 1
  },
  "resolvers": [
    {
      "ip": "103.18.138.20",
      "version": 4,
      "country_code": "nz",
      "country": "New Zealand",
      "continent_code": "oc",
      "continent": "Oceania",
      "organization": "The Virus Centre Network",
      "domain": null,
      "trusted": false,
      "anycast": false,
      "dnssec": {
        "aware": true,
        "validating": false
      },
      "blocking": {
        "ads": false,
        "malware": false,
        "adult": false
      },
      "uptime": {
        "24h": 100.0,
        "30d": 91.14,
        "90d": 88.49,
        "1y": 95.24
      }
    }
  ]
}
