{
  "metadata": {
    "country_code": "om",
    "country_name": "Oman",
    "continent_code": "as",
    "continent_name": "Asia",
    "generated_at": "2026-04-10T18:13:34Z",
    "total_servers": 5
  },
  "resolvers": [
    {
      "ip": "46.40.244.136",
      "version": 4,
      "country_code": "om",
      "country": "Oman",
      "continent_code": "as",
      "continent": "Asia",
      "organization": "Nawras (Oman)",
      "domain": null,
      "trusted": false,
      "anycast": false,
      "dnssec": {
        "aware": true,
        "validating": true
      },
      "blocking": {
        "ads": false,
        "malware": true,
        "adult": true
      },
      "uptime": {
        "24h": 100.0,
        "30d": 96.19,
        "90d": 96.19,
        "1y": 96.19
      }
    },
    {
      "ip": "188.135.49.95",
      "version": 4,
      "country_code": "om",
      "country": "Oman",
      "continent_code": "as",
      "continent": "Asia",
      "organization": "Nawras",
      "domain": null,
      "trusted": false,
      "anycast": false,
      "dnssec": {
        "aware": true,
        "validating": false
      },
      "blocking": {
        "ads": true,
        "malware": true,
        "adult": true
      },
      "uptime": {
        "24h": 69.23,
        "30d": 58.74,
        "90d": 71.68,
        "1y": 81.09
      }
    },
    {
      "ip": "188.135.14.80",
      "version": 4,
      "country_code": "om",
      "country": "Oman",
      "continent_code": "as",
      "continent": "Asia",
      "organization": "Nawras",
      "domain": null,
      "trusted": false,
      "anycast": false,
      "dnssec": {
        "aware": true,
        "validating": false
      },
      "blocking": {
        "ads": true,
        "malware": true,
        "adult": true
      },
      "uptime": {
        "24h": 35.71,
        "30d": 32.05,
        "90d": 39.94,
        "1y": 35.31
      }
    },
    {
      "ip": "46.40.214.43",
      "version": 4,
      "country_code": "om",
      "country": "Oman",
      "continent_code": "as",
      "continent": "Asia",
      "organization": "Nawras (Oman)",
      "domain": null,
      "trusted": false,
      "anycast": false,
      "dnssec": {
        "aware": true,
        "validating": false
      },
      "blocking": {
        "ads": true,
        "malware": true,
        "adult": true
      },
      "uptime": {
        "24h": 46.15,
        "30d": 55.93,
        "90d": 39.85,
        "1y": 59.1
      }
    },
    {
      "ip": "46.40.204.50",
      "version": 4,
      "country_code": "om",
      "country": "Oman",
      "continent_code": "as",
      "continent": "Asia",
      "organization": "Nawras (Oman)",
      "domain": null,
      "trusted": false,
      "anycast": false,
      "dnssec": {
        "aware": true,
        "validating": false
      },
      "blocking": {
        "ads": true,
        "malware": true,
        "adult": true
      },
      "uptime": {
        "24h": 64.29,
        "30d": 80.35,
        "90d": 82.98,
        "1y": 82.98
      }
    }
  ]
}
