{
  "metadata": {
    "country_code": "sv",
    "country_name": "El Salvador",
    "continent_code": "na",
    "continent_name": "North America",
    "generated_at": "2026-04-10T18:13:34Z",
    "total_servers": 4
  },
  "resolvers": [
    {
      "ip": "201.247.112.236",
      "version": 4,
      "country_code": "sv",
      "country": "El Salvador",
      "continent_code": "na",
      "continent": "North America",
      "organization": "LAB. PAILL DIV. DE GRUPO PAILL, S.A. DE C.V",
      "domain": null,
      "trusted": false,
      "anycast": false,
      "dnssec": {
        "aware": true,
        "validating": false
      },
      "blocking": {
        "ads": false,
        "malware": false,
        "adult": false
      },
      "uptime": {
        "24h": 57.14,
        "30d": 79.69,
        "90d": 82.82,
        "1y": 80.52
      }
    },
    {
      "ip": "168.243.48.33",
      "version": 4,
      "country_code": "sv",
      "country": "El Salvador",
      "continent_code": "na",
      "continent": "North America",
      "organization": "SVNet",
      "domain": "ns.telcom.com.sv",
      "trusted": false,
      "anycast": false,
      "dnssec": {
        "aware": true,
        "validating": false
      },
      "blocking": {
        "ads": false,
        "malware": true,
        "adult": true
      },
      "uptime": {
        "24h": 69.23,
        "30d": 88.08,
        "90d": 95.17,
        "1y": 97.84
      }
    },
    {
      "ip": "190.86.205.194",
      "version": 4,
      "country_code": "sv",
      "country": "El Salvador",
      "continent_code": "na",
      "continent": "North America",
      "organization": "Sociedad Cooperativa EX Banco Cuscatlan. De R.L",
      "domain": "ns1.coopex.com.sv",
      "trusted": false,
      "anycast": false,
      "dnssec": {
        "aware": true,
        "validating": false
      },
      "blocking": {
        "ads": true,
        "malware": true,
        "adult": true
      },
      "uptime": {
        "24h": 69.23,
        "30d": 66.45,
        "90d": 79.27,
        "1y": 81.4
      }
    },
    {
      "ip": "200.85.7.28",
      "version": 4,
      "country_code": "sv",
      "country": "El Salvador",
      "continent_code": "na",
      "continent": "North America",
      "organization": "Telemovil El Salvador S.A",
      "domain": "ftp.grupotropigas.com.sv",
      "trusted": false,
      "anycast": false,
      "dnssec": {
        "aware": true,
        "validating": true
      },
      "blocking": {
        "ads": false,
        "malware": false,
        "adult": false
      },
      "uptime": {
        "24h": 100.0,
        "30d": 100.0,
        "90d": 99.66,
        "1y": 98.64
      }
    }
  ]
}
