{
  "metadata": {
    "country_code": "ye",
    "country_name": "Yemen",
    "continent_code": "as",
    "continent_name": "Asia",
    "generated_at": "2026-04-17T06:47:16Z",
    "total_servers": 7
  },
  "resolvers": [
    {
      "ip": "5.255.17.43",
      "version": 4,
      "country_code": "ye",
      "country": "Yemen",
      "continent_code": "as",
      "continent": "Asia",
      "organization": "Aljoraf area - Airport street",
      "domain": null,
      "trusted": false,
      "anycast": false,
      "dnssec": {
        "aware": false,
        "validating": false
      },
      "blocking": {
        "ads": true,
        "malware": true,
        "adult": true
      },
      "uptime": {
        "24h": 16.67,
        "30d": 29.17,
        "90d": 17.6,
        "1y": 16.13
      }
    },
    {
      "ip": "178.130.94.122",
      "version": 4,
      "country_code": "ye",
      "country": "Yemen",
      "continent_code": "as",
      "continent": "Asia",
      "organization": "Aljoraf area - Airport street",
      "domain": null,
      "trusted": false,
      "anycast": false,
      "dnssec": {
        "aware": false,
        "validating": false
      },
      "blocking": {
        "ads": true,
        "malware": true,
        "adult": true
      },
      "uptime": {
        "24h": 85.71,
        "30d": 25.0,
        "90d": 18.7,
        "1y": 17.75
      }
    },
    {
      "ip": "178.130.71.118",
      "version": 4,
      "country_code": "ye",
      "country": "Yemen",
      "continent_code": "as",
      "continent": "Asia",
      "organization": "Aljoraf area - Airport street",
      "domain": null,
      "trusted": false,
      "anycast": false,
      "dnssec": {
        "aware": false,
        "validating": false
      },
      "blocking": {
        "ads": false,
        "malware": true,
        "adult": false
      },
      "uptime": {
        "24h": 100.0,
        "30d": 35.0,
        "90d": 24.11,
        "1y": 14.06
      }
    },
    {
      "ip": "175.110.37.39",
      "version": 4,
      "country_code": "ye",
      "country": "Yemen",
      "continent_code": "as",
      "continent": "Asia",
      "organization": "Public Telecommunication Corporation",
      "domain": null,
      "trusted": false,
      "anycast": false,
      "dnssec": {
        "aware": false,
        "validating": false
      },
      "blocking": {
        "ads": true,
        "malware": true,
        "adult": true
      },
      "uptime": {
        "24h": 100.0,
        "30d": 15.0,
        "90d": 15.97,
        "1y": 8.93
      }
    },
    {
      "ip": "94.26.222.232",
      "version": 4,
      "country_code": "ye",
      "country": "Yemen",
      "continent_code": "as",
      "continent": "Asia",
      "organization": "Aljoraf area - Airport street",
      "domain": null,
      "trusted": false,
      "anycast": false,
      "dnssec": {
        "aware": false,
        "validating": false
      },
      "blocking": {
        "ads": true,
        "malware": true,
        "adult": true
      },
      "uptime": {
        "24h": 100.0,
        "30d": 35.56,
        "90d": 28.99,
        "1y": 32.69
      }
    },
    {
      "ip": "5.255.11.206",
      "version": 4,
      "country_code": "ye",
      "country": "Yemen",
      "continent_code": "as",
      "continent": "Asia",
      "organization": "Aljoraf area - Airport street",
      "domain": null,
      "trusted": false,
      "anycast": false,
      "dnssec": {
        "aware": true,
        "validating": false
      },
      "blocking": {
        "ads": true,
        "malware": true,
        "adult": true
      },
      "uptime": {
        "24h": 100.0,
        "30d": 25.58,
        "90d": 30.77,
        "1y": 17.79
      }
    },
    {
      "ip": "5.255.29.223",
      "version": 4,
      "country_code": "ye",
      "country": "Yemen",
      "continent_code": "as",
      "continent": "Asia",
      "organization": "Aljoraf area - Airport street",
      "domain": null,
      "trusted": false,
      "anycast": false,
      "dnssec": {
        "aware": false,
        "validating": false
      },
      "blocking": {
        "ads": true,
        "malware": true,
        "adult": true
      },
      "uptime": {
        "24h": 100.0,
        "30d": 10.53,
        "90d": 13.49,
        "1y": 17.4
      }
    }
  ]
}
